snakemake_executor_plugin_aws_basic_batch/__init__.py
snakemake_executor_plugin_aws_basic_batch/batch_client.py
snakemake_executor_plugin_aws_basic_batch-0.1.0.dist-info/METADATA
snakemake_executor_plugin_aws_basic_batch-0.1.0.dist-info/WHEEL
snakemake_executor_plugin_aws_basic_batch-0.1.0.dist-info/licenses/LICENSE
snakemake_executor_plugin_aws_basic_batch-0.1.0.dist-info/RECORD
