Metadata-Version: 2.4
Name: snakemake-executor-plugin-aws-basic-batch
Version: 0.1.0
Project-URL: Repository, https://github.com/radusuciu/snakemake-executor-plugin-aws-basic-batch
Author-email: Radu Suciu <radusuciu@gmail.com>
License-File: LICENSE
Requires-Python: <4.0,>=3.11
Requires-Dist: boto3>=1.26.0
Requires-Dist: snakemake-interface-common<2,>=1.22.0
Requires-Dist: snakemake-interface-executor-plugins<10,>=9.3.9
Requires-Dist: snakemake-storage-plugin-s3>=0.3.6
Requires-Dist: snakemake>=9.14.0
